[
    { "name": "Drone-0301", "controlBit": true, "status" : "On Route", "time": "00:00:00", "battery": 75, "routeId": 1},
    { "name": "Drone-0302", "controlBit": false, "status" : "Returning", "time": "00:00:00", "battery": 100, "routeId": 2},
    { "name": "Drone-0303", "controlBit": true, "status" : "On Route", "time": "00:00:00", "battery": 15, "routeId": 3},
    { "name": "Drone-0304", "controlBit": true, "status" : "On Route", "time": "00:00:00", "battery": 23, "routeId": 4},
    { "name": "Drone-0305", "controlBit": false, "status" : "Returning", "time": "00:00:00", "battery": 50, "routeId": 5},
    { "name": "Drone-0401", "controlBit": false, "status" : "Stopped", "time": "00:00:00", "battery": 95, "routeId": 6},
    { "name": "Drone-0402", "controlBit": true, "status" : "Stopped", "time": "00:00:00", "battery": 37, "routeId": 7},
    { "name": "Robot-0001", "controlBit": true, "status" : "On Route", "time": "00:00:00", "battery": 64, "routeId": 8},
    { "name": "Robot-0101", "controlBit": false, "status" : "Returning", "time": "00:00:00", "battery": 9, "routeId": 9},
    { "name": "Robot-0201", "controlBit": true, "status" : "Stopped", "time": "00:00:00", "battery": 40, "routeId": 10}
]